{
   "runs" : [
      {
         "OS" : "linux",
         "abstract" : "Information about the CGI environment",
         "dir" : "/home/runner/work/CGI-Info/CGI-Info",
         "finish" : 1756516434.34238,
         "name" : "CGI-Info",
         "perl" : "5.40.3",
         "run" : "-e",
         "start" : 1756516434.34205,
         "version" : "1.06"
      },
      {
         "OS" : "linux",
         "abstract" : "Information about the CGI environment",
         "dir" : "/home/runner/work/CGI-Info/CGI-Info",
         "finish" : 1756516434.51052,
         "name" : "CGI-Info",
         "perl" : "5.40.3",
         "run" : "-e",
         "start" : 1756516434.5103,
         "version" : "1.06"
      },
      {
         "OS" : "linux",
         "abstract" : "Information about the CGI environment",
         "dir" : "/home/runner/work/CGI-Info/CGI-Info",
         "finish" : 1756516434.67654,
         "name" : "CGI-Info",
         "perl" : "5.40.3",
         "run" : "-e",
         "start" : 1756516434.67627,
         "version" : "1.06"
      },
      {
         "OS" : "linux",
         "abstract" : "Information about the CGI environment",
         "dir" : "/home/runner/work/CGI-Info/CGI-Info",
         "finish" : 1756516434.84018,
         "name" : "CGI-Info",
         "perl" : "5.40.3",
         "run" : "-e",
         "start" : 1756516434.8399,
         "version" : "1.06"
      },
      {
         "OS" : "linux",
         "abstract" : "Information about the CGI environment",
         "dir" : "/home/runner/work/CGI-Info/CGI-Info",
         "finish" : 1756516435.00447,
         "name" : "CGI-Info",
         "perl" : "5.40.3",
         "run" : "-e",
         "start" : 1756516435.00427,
         "version" : "1.06"
      },
      {
         "OS" : "linux",
         "abstract" : "Information about the CGI environment",
         "dir" : "/home/runner/work/CGI-Info/CGI-Info",
         "finish" : 1756516435.16848,
         "name" : "CGI-Info",
         "perl" : "5.40.3",
         "run" : "-e",
         "start" : 1756516435.16828,
         "version" : "1.06"
      },
      {
         "OS" : "linux",
         "abstract" : "Information about the CGI environment",
         "dir" : "/home/runner/work/CGI-Info/CGI-Info",
         "finish" : 1756516435.33335,
         "name" : "CGI-Info",
         "perl" : "5.40.3",
         "run" : "-e",
         "start" : 1756516435.33313,
         "version" : "1.06"
      },
      {
         "OS" : "linux",
         "abstract" : "Information about the CGI environment",
         "dir" : "/home/runner/work/CGI-Info/CGI-Info",
         "finish" : 1756516435.49773,
         "name" : "CGI-Info",
         "perl" : "5.40.3",
         "run" : "-e",
         "start" : 1756516435.49753,
         "version" : "1.06"
      },
      {
         "OS" : "linux",
         "abstract" : "Information about the CGI environment",
         "dir" : "/home/runner/work/CGI-Info/CGI-Info",
         "finish" : 1756516435.68297,
         "name" : "CGI-Info",
         "perl" : "5.40.3",
         "run" : "-e",
         "start" : 1756516435.66976,
         "version" : "1.06"
      },
      {
         "OS" : "linux",
         "abstract" : "Information about the CGI environment",
         "dir" : "/home/runner/work/CGI-Info/CGI-Info",
         "finish" : 1756516463.79053,
         "name" : "CGI-Info",
         "perl" : "5.40.3",
         "run" : "-e",
         "start" : 1756516435.88024,
         "version" : "1.06"
      },
      {
         "OS" : "linux",
         "abstract" : "Information about the CGI environment",
         "dir" : "/home/runner/work/CGI-Info/CGI-Info",
         "finish" : 1756516436.02694,
         "name" : "CGI-Info",
         "perl" : "5.40.3",
         "run" : "-e",
         "start" : 1756516436.02685,
         "version" : "1.06"
      },
      {
         "OS" : "linux",
         "abstract" : "Information about the CGI environment",
         "dir" : "/home/runner/work/CGI-Info/CGI-Info",
         "finish" : 1756516436.37328,
         "name" : "CGI-Info",
         "perl" : "5.40.3",
         "run" : "t/00-load.t",
         "start" : 1756516436.3722,
         "version" : "1.06"
      },
      {
         "OS" : "linux",
         "abstract" : "Information about the CGI environment",
         "dir" : "/home/runner/work/CGI-Info/CGI-Info",
         "finish" : 1756516437.08773,
         "name" : "CGI-Info",
         "perl" : "5.40.3",
         "run" : "t/10-compile.t",
         "start" : 1756516436.83582,
         "version" : "1.06"
      },
      {
         "OS" : "linux",
         "abstract" : "Information about the CGI environment",
         "dir" : "/home/runner/work/CGI-Info/CGI-Info",
         "finish" : 1756516437.46831,
         "name" : "CGI-Info",
         "perl" : "5.40.3",
         "run" : "t/20-new.t",
         "start" : 1756516437.43897,
         "version" : "1.06"
      },
      {
         "OS" : "linux",
         "abstract" : "Information about the CGI environment",
         "dir" : "/home/runner/work/CGI-Info/CGI-Info",
         "finish" : 1756516438.14845,
         "name" : "CGI-Info",
         "perl" : "5.40.3",
         "run" : "t/30-basics.t",
         "start" : 1756516438.03678,
         "version" : "1.06"
      },
      {
         "OS" : "linux",
         "abstract" : "Information about the CGI environment",
         "dir" : "/home/runner/work/CGI-Info/CGI-Info",
         "finish" : 1756516438.66769,
         "name" : "CGI-Info",
         "perl" : "5.40.3",
         "run" : "t/40-more.t",
         "start" : 1756516438.6675,
         "version" : "1.06"
      },
      {
         "OS" : "linux",
         "abstract" : "Information about the CGI environment",
         "dir" : "/home/runner/work/CGI-Info/CGI-Info",
         "finish" : 1756516439.1065,
         "name" : "CGI-Info",
         "perl" : "5.40.3",
         "run" : "t/allow.t",
         "start" : 1756516439.01701,
         "version" : "1.06"
      },
      {
         "OS" : "linux",
         "abstract" : "Information about the CGI environment",
         "dir" : "/home/runner/work/CGI-Info/CGI-Info",
         "finish" : 1756516439.55507,
         "name" : "CGI-Info",
         "perl" : "5.40.3",
         "run" : "t/apoc.t",
         "start" : 1756516439.55504,
         "version" : "1.06"
      },
      {
         "OS" : "linux",
         "abstract" : "Information about the CGI environment",
         "dir" : "/home/runner/work/CGI-Info/CGI-Info",
         "finish" : 1756516439.92148,
         "name" : "CGI-Info",
         "perl" : "5.40.3",
         "run" : "t/as_string.t",
         "start" : 1756516439.88433,
         "version" : "1.06"
      },
      {
         "OS" : "linux",
         "abstract" : "Information about the CGI environment",
         "dir" : "/home/runner/work/CGI-Info/CGI-Info",
         "finish" : 1756516441.20921,
         "name" : "CGI-Info",
         "perl" : "5.40.3",
         "run" : "t/bin.t",
         "start" : 1756516440.43057,
         "version" : "1.06"
      },
      {
         "OS" : "linux",
         "abstract" : "Information about the CGI environment",
         "dir" : "/home/runner/work/CGI-Info/CGI-Info",
         "finish" : 1756516440.95531,
         "name" : "CGI-Info",
         "perl" : "5.40.3",
         "run" : "bin/info.pl",
         "start" : 1756516440.92549,
         "version" : "1.06"
      },
      {
         "OS" : "linux",
         "abstract" : "Information about the CGI environment",
         "dir" : "/home/runner/work/CGI-Info/CGI-Info",
         "finish" : 1756516441.5053,
         "name" : "CGI-Info",
         "perl" : "5.40.3",
         "run" : "t/boiler.t",
         "start" : 1756516441.48405,
         "version" : "1.06"
      },
      {
         "OS" : "linux",
         "abstract" : "Information about the CGI environment",
         "dir" : "/home/runner/work/CGI-Info/CGI-Info",
         "finish" : 1756516441.89929,
         "name" : "CGI-Info",
         "perl" : "5.40.3",
         "run" : "t/carp.t",
         "start" : 1756516441.85827,
         "version" : "1.06"
      },
      {
         "OS" : "linux",
         "abstract" : "Information about the CGI environment",
         "dir" : "/home/runner/work/CGI-Info/CGI-Info",
         "finish" : 1756516442.36801,
         "name" : "CGI-Info",
         "perl" : "5.40.3",
         "run" : "t/changes.t",
         "start" : 1756516442.36783,
         "version" : "1.06"
      },
      {
         "OS" : "linux",
         "abstract" : "Information about the CGI environment",
         "dir" : "/home/runner/work/CGI-Info/CGI-Info",
         "finish" : 1756516442.60069,
         "name" : "CGI-Info",
         "perl" : "5.40.3",
         "run" : "t/comment-spelling.t",
         "start" : 1756516442.60051,
         "version" : "1.06"
      },
      {
         "OS" : "linux",
         "abstract" : "Information about the CGI environment",
         "dir" : "/home/runner/work/CGI-Info/CGI-Info",
         "finish" : 1756516442.96374,
         "name" : "CGI-Info",
         "perl" : "5.40.3",
         "run" : "t/config_file.t",
         "start" : 1756516442.86734,
         "version" : "1.06"
      },
      {
         "OS" : "linux",
         "abstract" : "Information about the CGI environment",
         "dir" : "/home/runner/work/CGI-Info/CGI-Info",
         "finish" : 1756516443.58564,
         "name" : "CGI-Info",
         "perl" : "5.40.3",
         "run" : "t/cookies.t",
         "start" : 1756516443.54056,
         "version" : "1.06"
      },
      {
         "OS" : "linux",
         "abstract" : "Information about the CGI environment",
         "dir" : "/home/runner/work/CGI-Info/CGI-Info",
         "finish" : 1756516444.05738,
         "name" : "CGI-Info",
         "perl" : "5.40.3",
         "run" : "t/cover.t",
         "start" : 1756516444.05718,
         "version" : "1.06"
      },
      {
         "OS" : "linux",
         "abstract" : "Information about the CGI environment",
         "dir" : "/home/runner/work/CGI-Info/CGI-Info",
         "finish" : 1756516444.28974,
         "name" : "CGI-Info",
         "perl" : "5.40.3",
         "run" : "t/critic.t",
         "start" : 1756516444.28956,
         "version" : "1.06"
      },
      {
         "OS" : "linux",
         "abstract" : "Information about the CGI environment",
         "dir" : "/home/runner/work/CGI-Info/CGI-Info",
         "finish" : 1756516444.52181,
         "name" : "CGI-Info",
         "perl" : "5.40.3",
         "run" : "t/cv.t",
         "start" : 1756516444.52161,
         "version" : "1.06"
      },
      {
         "OS" : "linux",
         "abstract" : "Information about the CGI environment",
         "dir" : "/home/runner/work/CGI-Info/CGI-Info",
         "finish" : 1756516444.75338,
         "name" : "CGI-Info",
         "perl" : "5.40.3",
         "run" : "t/dependent-modules.t",
         "start" : 1756516444.75317,
         "version" : "1.06"
      },
      {
         "OS" : "linux",
         "abstract" : "Information about the CGI environment",
         "dir" : "/home/runner/work/CGI-Info/CGI-Info",
         "finish" : 1756516444.98615,
         "name" : "CGI-Info",
         "perl" : "5.40.3",
         "run" : "t/dist.t",
         "start" : 1756516444.98597,
         "version" : "1.06"
      },
      {
         "OS" : "linux",
         "abstract" : "Information about the CGI environment",
         "dir" : "/home/runner/work/CGI-Info/CGI-Info",
         "finish" : 1756516445.21941,
         "name" : "CGI-Info",
         "perl" : "5.40.3",
         "run" : "t/eof.t",
         "start" : 1756516445.21922,
         "version" : "1.06"
      },
      {
         "OS" : "linux",
         "abstract" : "Information about the CGI environment",
         "dir" : "/home/runner/work/CGI-Info/CGI-Info",
         "finish" : 1756516445.45339,
         "name" : "CGI-Info",
         "perl" : "5.40.3",
         "run" : "t/eol.t",
         "start" : 1756516445.45319,
         "version" : "1.06"
      },
      {
         "OS" : "linux",
         "abstract" : "Information about the CGI environment",
         "dir" : "/home/runner/work/CGI-Info/CGI-Info",
         "finish" : 1756516445.71005,
         "name" : "CGI-Info",
         "perl" : "5.40.3",
         "run" : "t/expect.t",
         "start" : 1756516445.70938,
         "version" : "1.06"
      },
      {
         "OS" : "linux",
         "abstract" : "Information about the CGI environment",
         "dir" : "/home/runner/work/CGI-Info/CGI-Info",
         "finish" : 1756516445.95533,
         "name" : "CGI-Info",
         "perl" : "5.40.3",
         "run" : "t/fixme.t",
         "start" : 1756516445.95514,
         "version" : "1.06"
      },
      {
         "OS" : "linux",
         "abstract" : "Information about the CGI environment",
         "dir" : "/home/runner/work/CGI-Info/CGI-Info",
         "finish" : 1756516446.18773,
         "name" : "CGI-Info",
         "perl" : "5.40.3",
         "run" : "t/gv.t",
         "start" : 1756516446.18755,
         "version" : "1.06"
      },
      {
         "OS" : "linux",
         "abstract" : "Information about the CGI environment",
         "dir" : "/home/runner/work/CGI-Info/CGI-Info",
         "finish" : 1756516446.58606,
         "name" : "CGI-Info",
         "perl" : "5.40.3",
         "run" : "t/is_mobile.t",
         "start" : 1756516446.53209,
         "version" : "1.06"
      },
      {
         "OS" : "linux",
         "abstract" : "Information about the CGI environment",
         "dir" : "/home/runner/work/CGI-Info/CGI-Info",
         "finish" : 1756516447.2161,
         "name" : "CGI-Info",
         "perl" : "5.40.3",
         "run" : "t/is_robot.t",
         "start" : 1756516447.16451,
         "version" : "1.06"
      },
      {
         "OS" : "linux",
         "abstract" : "Information about the CGI environment",
         "dir" : "/home/runner/work/CGI-Info/CGI-Info",
         "finish" : 1756516447.85611,
         "name" : "CGI-Info",
         "perl" : "5.40.3",
         "run" : "t/is_search.t",
         "start" : 1756516447.80227,
         "version" : "1.06"
      },
      {
         "OS" : "linux",
         "abstract" : "Information about the CGI environment",
         "dir" : "/home/runner/work/CGI-Info/CGI-Info",
         "finish" : 1756516448.47767,
         "name" : "CGI-Info",
         "perl" : "5.40.3",
         "run" : "t/is_tablet.t",
         "start" : 1756516448.43652,
         "version" : "1.06"
      },
      {
         "OS" : "linux",
         "abstract" : "Information about the CGI environment",
         "dir" : "/home/runner/work/CGI-Info/CGI-Info",
         "finish" : 1756516449.07124,
         "name" : "CGI-Info",
         "perl" : "5.40.3",
         "run" : "t/json.t",
         "start" : 1756516449.04883,
         "version" : "1.06"
      },
      {
         "OS" : "linux",
         "abstract" : "Information about the CGI environment",
         "dir" : "/home/runner/work/CGI-Info/CGI-Info",
         "finish" : 1756516449.53265,
         "name" : "CGI-Info",
         "perl" : "5.40.3",
         "run" : "t/kwalitee.t",
         "start" : 1756516449.53246,
         "version" : "1.06"
      },
      {
         "OS" : "linux",
         "abstract" : "Information about the CGI environment",
         "dir" : "/home/runner/work/CGI-Info/CGI-Info",
         "finish" : 1756516449.90815,
         "name" : "CGI-Info",
         "perl" : "5.40.3",
         "run" : "t/logdir.t",
         "start" : 1756516449.88164,
         "version" : "1.06"
      },
      {
         "OS" : "linux",
         "abstract" : "Information about the CGI environment",
         "dir" : "/home/runner/work/CGI-Info/CGI-Info",
         "finish" : 1756516450.51279,
         "name" : "CGI-Info",
         "perl" : "5.40.3",
         "run" : "t/logger.t",
         "start" : 1756516450.4811,
         "version" : "1.06"
      },
      {
         "OS" : "linux",
         "abstract" : "Information about the CGI environment",
         "dir" : "/home/runner/work/CGI-Info/CGI-Info",
         "finish" : 1756516450.98149,
         "name" : "CGI-Info",
         "perl" : "5.40.3",
         "run" : "t/manifest.t",
         "start" : 1756516450.9813,
         "version" : "1.06"
      },
      {
         "OS" : "linux",
         "abstract" : "Information about the CGI environment",
         "dir" : "/home/runner/work/CGI-Info/CGI-Info",
         "finish" : 1756516451.21586,
         "name" : "CGI-Info",
         "perl" : "5.40.3",
         "run" : "t/metrics.t",
         "start" : 1756516451.21565,
         "version" : "1.06"
      },
      {
         "OS" : "linux",
         "abstract" : "Information about the CGI environment",
         "dir" : "/home/runner/work/CGI-Info/CGI-Info",
         "finish" : 1756516451.45324,
         "name" : "CGI-Info",
         "perl" : "5.40.3",
         "run" : "t/minimum.t",
         "start" : 1756516451.45298,
         "version" : "1.06"
      },
      {
         "OS" : "linux",
         "abstract" : "Information about the CGI environment",
         "dir" : "/home/runner/work/CGI-Info/CGI-Info",
         "finish" : 1756516451.69248,
         "name" : "CGI-Info",
         "perl" : "5.40.3",
         "run" : "t/modules-used.t",
         "start" : 1756516451.6922,
         "version" : "1.06"
      },
      {
         "OS" : "linux",
         "abstract" : "Information about the CGI environment",
         "dir" : "/home/runner/work/CGI-Info/CGI-Info",
         "finish" : 1756516451.93252,
         "name" : "CGI-Info",
         "perl" : "5.40.3",
         "run" : "t/namespaces.t",
         "start" : 1756516451.93225,
         "version" : "1.06"
      },
      {
         "OS" : "linux",
         "abstract" : "Information about the CGI environment",
         "dir" : "/home/runner/work/CGI-Info/CGI-Info",
         "finish" : 1756516452.17178,
         "name" : "CGI-Info",
         "perl" : "5.40.3",
         "run" : "t/no404s.t",
         "start" : 1756516452.17157,
         "version" : "1.06"
      },
      {
         "OS" : "linux",
         "abstract" : "Information about the CGI environment",
         "dir" : "/home/runner/work/CGI-Info/CGI-Info",
         "finish" : 1756516452.41171,
         "name" : "CGI-Info",
         "perl" : "5.40.3",
         "run" : "t/noopentickets.t",
         "start" : 1756516452.41147,
         "version" : "1.06"
      },
      {
         "OS" : "linux",
         "abstract" : "Information about the CGI environment",
         "dir" : "/home/runner/work/CGI-Info/CGI-Info",
         "finish" : 1756516452.65273,
         "name" : "CGI-Info",
         "perl" : "5.40.3",
         "run" : "t/noplan.t",
         "start" : 1756516452.6525,
         "version" : "1.06"
      },
      {
         "OS" : "linux",
         "abstract" : "Information about the CGI environment",
         "dir" : "/home/runner/work/CGI-Info/CGI-Info",
         "finish" : 1756516452.99159,
         "name" : "CGI-Info",
         "perl" : "5.40.3",
         "run" : "t/object_configure.t",
         "start" : 1756516452.92277,
         "version" : "1.06"
      },
      {
         "OS" : "linux",
         "abstract" : "Information about the CGI environment",
         "dir" : "/home/runner/work/CGI-Info/CGI-Info",
         "finish" : 1756516453.64118,
         "name" : "CGI-Info",
         "perl" : "5.40.3",
         "run" : "t/param.t",
         "start" : 1756516453.57288,
         "version" : "1.06"
      },
      {
         "OS" : "linux",
         "abstract" : "Information about the CGI environment",
         "dir" : "/home/runner/work/CGI-Info/CGI-Info",
         "finish" : 1756516454.42899,
         "name" : "CGI-Info",
         "perl" : "5.40.3",
         "run" : "t/params.t",
         "start" : 1756516454.2527,
         "version" : "1.06"
      },
      {
         "OS" : "linux",
         "abstract" : "Information about the CGI environment",
         "dir" : "/home/runner/work/CGI-Info/CGI-Info",
         "finish" : 1756516454.98139,
         "name" : "CGI-Info",
         "perl" : "5.40.3",
         "run" : "t/pod-cm.t",
         "start" : 1756516454.9811,
         "version" : "1.06"
      },
      {
         "OS" : "linux",
         "abstract" : "Information about the CGI environment",
         "dir" : "/home/runner/work/CGI-Info/CGI-Info",
         "finish" : 1756516455.2253,
         "name" : "CGI-Info",
         "perl" : "5.40.3",
         "run" : "t/pod-coverage.t",
         "start" : 1756516455.225,
         "version" : "1.06"
      },
      {
         "OS" : "linux",
         "abstract" : "Information about the CGI environment",
         "dir" : "/home/runner/work/CGI-Info/CGI-Info",
         "finish" : 1756516455.46684,
         "name" : "CGI-Info",
         "perl" : "5.40.3",
         "run" : "t/pod-links.t",
         "start" : 1756516455.4666,
         "version" : "1.06"
      },
      {
         "OS" : "linux",
         "abstract" : "Information about the CGI environment",
         "dir" : "/home/runner/work/CGI-Info/CGI-Info",
         "finish" : 1756516455.71303,
         "name" : "CGI-Info",
         "perl" : "5.40.3",
         "run" : "t/pod-snippets.t",
         "start" : 1756516455.71277,
         "version" : "1.06"
      },
      {
         "OS" : "linux",
         "abstract" : "Information about the CGI environment",
         "dir" : "/home/runner/work/CGI-Info/CGI-Info",
         "finish" : 1756516455.95266,
         "name" : "CGI-Info",
         "perl" : "5.40.3",
         "run" : "t/pod-spelling.t",
         "start" : 1756516455.95242,
         "version" : "1.06"
      },
      {
         "OS" : "linux",
         "abstract" : "Information about the CGI environment",
         "dir" : "/home/runner/work/CGI-Info/CGI-Info",
         "finish" : 1756516456.19309,
         "name" : "CGI-Info",
         "perl" : "5.40.3",
         "run" : "t/pod-synopsis.t",
         "start" : 1756516456.19282,
         "version" : "1.06"
      },
      {
         "OS" : "linux",
         "abstract" : "Information about the CGI environment",
         "dir" : "/home/runner/work/CGI-Info/CGI-Info",
         "finish" : 1756516456.43187,
         "name" : "CGI-Info",
         "perl" : "5.40.3",
         "run" : "t/pod.t",
         "start" : 1756516456.43168,
         "version" : "1.06"
      },
      {
         "OS" : "linux",
         "abstract" : "Information about the CGI environment",
         "dir" : "/home/runner/work/CGI-Info/CGI-Info",
         "finish" : 1756516456.69817,
         "name" : "CGI-Info",
         "perl" : "5.40.3",
         "run" : "t/port.t",
         "start" : 1756516456.69794,
         "version" : "1.06"
      },
      {
         "OS" : "linux",
         "abstract" : "Information about the CGI environment",
         "dir" : "/home/runner/work/CGI-Info/CGI-Info",
         "finish" : 1756516456.94694,
         "name" : "CGI-Info",
         "perl" : "5.40.3",
         "run" : "t/prereq.t",
         "start" : 1756516456.94667,
         "version" : "1.06"
      },
      {
         "OS" : "linux",
         "abstract" : "Information about the CGI environment",
         "dir" : "/home/runner/work/CGI-Info/CGI-Info",
         "finish" : 1756516457.33445,
         "name" : "CGI-Info",
         "perl" : "5.40.3",
         "run" : "t/protocol.t",
         "start" : 1756516457.29669,
         "version" : "1.06"
      },
      {
         "OS" : "linux",
         "abstract" : "Information about the CGI environment",
         "dir" : "/home/runner/work/CGI-Info/CGI-Info",
         "finish" : 1756516457.95421,
         "name" : "CGI-Info",
         "perl" : "5.40.3",
         "run" : "t/rootdir.t",
         "start" : 1756516457.92196,
         "version" : "1.06"
      },
      {
         "OS" : "linux",
         "abstract" : "Information about the CGI environment",
         "dir" : "/home/runner/work/CGI-Info/CGI-Info",
         "finish" : 1756516458.59644,
         "name" : "CGI-Info",
         "perl" : "5.40.3",
         "run" : "t/script.t",
         "start" : 1756516458.54085,
         "version" : "1.06"
      },
      {
         "OS" : "linux",
         "abstract" : "Information about the CGI environment",
         "dir" : "/home/runner/work/CGI-Info/CGI-Info",
         "finish" : 1756516459.24925,
         "name" : "CGI-Info",
         "perl" : "5.40.3",
         "run" : "t/site.t",
         "start" : 1756516459.21346,
         "version" : "1.06"
      },
      {
         "OS" : "linux",
         "abstract" : "Information about the CGI environment",
         "dir" : "/home/runner/work/CGI-Info/CGI-Info",
         "finish" : 1756516459.87953,
         "name" : "CGI-Info",
         "perl" : "5.40.3",
         "run" : "t/status.t",
         "start" : 1756516459.83743,
         "version" : "1.06"
      },
      {
         "OS" : "linux",
         "abstract" : "Information about the CGI environment",
         "dir" : "/home/runner/work/CGI-Info/CGI-Info",
         "finish" : 1756516460.36456,
         "name" : "CGI-Info",
         "perl" : "5.40.3",
         "run" : "t/strict.t",
         "start" : 1756516460.36433,
         "version" : "1.06"
      },
      {
         "OS" : "linux",
         "abstract" : "Information about the CGI environment",
         "dir" : "/home/runner/work/CGI-Info/CGI-Info",
         "finish" : 1756516460.60603,
         "name" : "CGI-Info",
         "perl" : "5.40.3",
         "run" : "t/tabs.t",
         "start" : 1756516460.60577,
         "version" : "1.06"
      },
      {
         "OS" : "linux",
         "abstract" : "Information about the CGI environment",
         "dir" : "/home/runner/work/CGI-Info/CGI-Info",
         "finish" : 1756516460.8479,
         "name" : "CGI-Info",
         "perl" : "5.40.3",
         "run" : "t/taint.t",
         "start" : 1756516460.84768,
         "version" : "1.06"
      },
      {
         "OS" : "linux",
         "abstract" : "Information about the CGI environment",
         "dir" : "/home/runner/work/CGI-Info/CGI-Info",
         "finish" : 1756516461.24273,
         "name" : "CGI-Info",
         "perl" : "5.40.3",
         "run" : "t/tmpdir.t",
         "start" : 1756516461.19923,
         "version" : "1.06"
      },
      {
         "OS" : "linux",
         "abstract" : "Information about the CGI environment",
         "dir" : "/home/runner/work/CGI-Info/CGI-Info",
         "finish" : 1756516461.74865,
         "name" : "CGI-Info",
         "perl" : "5.40.3",
         "run" : "t/untaint.t",
         "start" : 1756516461.74822,
         "version" : "1.06"
      },
      {
         "OS" : "linux",
         "abstract" : "Information about the CGI environment",
         "dir" : "/home/runner/work/CGI-Info/CGI-Info",
         "finish" : 1756516461.99397,
         "name" : "CGI-Info",
         "perl" : "5.40.3",
         "run" : "t/unused.t",
         "start" : 1756516461.99377,
         "version" : "1.06"
      },
      {
         "OS" : "linux",
         "abstract" : "Information about the CGI environment",
         "dir" : "/home/runner/work/CGI-Info/CGI-Info",
         "finish" : 1756516462.23302,
         "name" : "CGI-Info",
         "perl" : "5.40.3",
         "run" : "t/vars.t",
         "start" : 1756516462.23276,
         "version" : "1.06"
      },
      {
         "OS" : "linux",
         "abstract" : "Information about the CGI environment",
         "dir" : "/home/runner/work/CGI-Info/CGI-Info",
         "finish" : 1756516462.47343,
         "name" : "CGI-Info",
         "perl" : "5.40.3",
         "run" : "t/version.t",
         "start" : 1756516462.47317,
         "version" : "1.06"
      },
      {
         "OS" : "linux",
         "abstract" : "Information about the CGI environment",
         "dir" : "/home/runner/work/CGI-Info/CGI-Info",
         "finish" : 1756516462.88013,
         "name" : "CGI-Info",
         "perl" : "5.40.3",
         "run" : "t/waf.t",
         "start" : 1756516462.82102,
         "version" : "1.06"
      },
      {
         "OS" : "linux",
         "abstract" : "Information about the CGI environment",
         "dir" : "/home/runner/work/CGI-Info/CGI-Info",
         "finish" : 1756516463.51185,
         "name" : "CGI-Info",
         "perl" : "5.40.3",
         "run" : "t/xml.t",
         "start" : 1756516463.48712,
         "version" : "1.06"
      }
   ],
   "summary" : {
      "Total" : {
         "branch" : {
            "covered" : 369,
            "error" : 119,
            "percentage" : 75.6147540983607,
            "total" : 488,
            "uncoverable" : 0
         },
         "condition" : {
            "covered" : 172,
            "error" : 121,
            "percentage" : 58.703071672355,
            "total" : 293,
            "uncoverable" : 0
         },
         "statement" : {
            "covered" : 689,
            "error" : 101,
            "percentage" : 87.2151898734177,
            "total" : 790
         },
         "subroutine" : {
            "covered" : 64,
            "error" : 1,
            "percentage" : 98.4615384615385,
            "total" : 65
         },
         "total" : {
            "covered" : 1294,
            "error" : 342,
            "percentage" : 79.0953545232274,
            "total" : 1636,
            "uncoverable" : 0
         }
      },
      "bin/info.pl" : {
         "branch" : {
            "covered" : 2,
            "error" : 6,
            "percentage" : 25,
            "total" : 8,
            "uncoverable" : 0
         },
         "statement" : {
            "covered" : 27,
            "error" : 9,
            "percentage" : 75,
            "total" : 36
         },
         "subroutine" : {
            "covered" : 3,
            "percentage" : 100,
            "total" : 3
         },
         "total" : {
            "covered" : 32,
            "error" : 15,
            "percentage" : 68.0851063829787,
            "total" : 47,
            "uncoverable" : 0
         }
      },
      "blib/lib/CGI/Info.pm" : {
         "branch" : {
            "covered" : 367,
            "error" : 113,
            "percentage" : 76.4583333333333,
            "total" : 480,
            "uncoverable" : 0
         },
         "condition" : {
            "covered" : 172,
            "error" : 121,
            "percentage" : 58.703071672355,
            "total" : 293,
            "uncoverable" : 0
         },
         "statement" : {
            "covered" : 662,
            "error" : 92,
            "percentage" : 87.7984084880637,
            "total" : 754
         },
         "subroutine" : {
            "covered" : 61,
            "error" : 1,
            "percentage" : 98.3870967741936,
            "total" : 62
         },
         "total" : {
            "covered" : 1262,
            "error" : 327,
            "percentage" : 79.4210195091252,
            "total" : 1589,
            "uncoverable" : 0
         }
      }
   }
}
