{
   "runs" : [
      {
         "OS" : "linux",
         "abstract" : "Information about the CGI environment",
         "dir" : "/home/runner/work/CGI-Info/CGI-Info",
         "finish" : 1769725365.03385,
         "name" : "CGI-Info",
         "perl" : "5.40.3",
         "run" : "-e",
         "start" : 1769725365.03352,
         "version" : "1.08"
      },
      {
         "OS" : "linux",
         "abstract" : "Information about the CGI environment",
         "dir" : "/home/runner/work/CGI-Info/CGI-Info",
         "finish" : 1769725365.19854,
         "name" : "CGI-Info",
         "perl" : "5.40.3",
         "run" : "-e",
         "start" : 1769725365.19833,
         "version" : "1.08"
      },
      {
         "OS" : "linux",
         "abstract" : "Information about the CGI environment",
         "dir" : "/home/runner/work/CGI-Info/CGI-Info",
         "finish" : 1769725365.36397,
         "name" : "CGI-Info",
         "perl" : "5.40.3",
         "run" : "-e",
         "start" : 1769725365.36366,
         "version" : "1.08"
      },
      {
         "OS" : "linux",
         "abstract" : "Information about the CGI environment",
         "dir" : "/home/runner/work/CGI-Info/CGI-Info",
         "finish" : 1769725365.52955,
         "name" : "CGI-Info",
         "perl" : "5.40.3",
         "run" : "-e",
         "start" : 1769725365.52923,
         "version" : "1.08"
      },
      {
         "OS" : "linux",
         "abstract" : "Information about the CGI environment",
         "dir" : "/home/runner/work/CGI-Info/CGI-Info",
         "finish" : 1769725365.69401,
         "name" : "CGI-Info",
         "perl" : "5.40.3",
         "run" : "-e",
         "start" : 1769725365.69378,
         "version" : "1.08"
      },
      {
         "OS" : "linux",
         "abstract" : "Information about the CGI environment",
         "dir" : "/home/runner/work/CGI-Info/CGI-Info",
         "finish" : 1769725365.85899,
         "name" : "CGI-Info",
         "perl" : "5.40.3",
         "run" : "-e",
         "start" : 1769725365.85874,
         "version" : "1.08"
      },
      {
         "OS" : "linux",
         "abstract" : "Information about the CGI environment",
         "dir" : "/home/runner/work/CGI-Info/CGI-Info",
         "finish" : 1769725366.02477,
         "name" : "CGI-Info",
         "perl" : "5.40.3",
         "run" : "-e",
         "start" : 1769725366.02452,
         "version" : "1.08"
      },
      {
         "OS" : "linux",
         "abstract" : "Information about the CGI environment",
         "dir" : "/home/runner/work/CGI-Info/CGI-Info",
         "finish" : 1769725366.1931,
         "name" : "CGI-Info",
         "perl" : "5.40.3",
         "run" : "-e",
         "start" : 1769725366.19288,
         "version" : "1.08"
      },
      {
         "OS" : "linux",
         "abstract" : "Information about the CGI environment",
         "dir" : "/home/runner/work/CGI-Info/CGI-Info",
         "finish" : 1769725366.38007,
         "name" : "CGI-Info",
         "perl" : "5.40.3",
         "run" : "-e",
         "start" : 1769725366.36676,
         "version" : "1.08"
      },
      {
         "OS" : "linux",
         "abstract" : "Information about the CGI environment",
         "dir" : "/home/runner/work/CGI-Info/CGI-Info",
         "finish" : 1769725394.90491,
         "name" : "CGI-Info",
         "perl" : "5.40.3",
         "run" : "-e",
         "start" : 1769725366.58029,
         "version" : "1.08"
      },
      {
         "OS" : "linux",
         "abstract" : "Information about the CGI environment",
         "dir" : "/home/runner/work/CGI-Info/CGI-Info",
         "finish" : 1769725366.72963,
         "name" : "CGI-Info",
         "perl" : "5.40.3",
         "run" : "-e",
         "start" : 1769725366.72951,
         "version" : "1.08"
      },
      {
         "OS" : "linux",
         "abstract" : "Information about the CGI environment",
         "dir" : "/home/runner/work/CGI-Info/CGI-Info",
         "finish" : 1769725367.08758,
         "name" : "CGI-Info",
         "perl" : "5.40.3",
         "run" : "t/00-load.t",
         "start" : 1769725367.08638,
         "version" : "1.08"
      },
      {
         "OS" : "linux",
         "abstract" : "Information about the CGI environment",
         "dir" : "/home/runner/work/CGI-Info/CGI-Info",
         "finish" : 1769725367.80856,
         "name" : "CGI-Info",
         "perl" : "5.40.3",
         "run" : "t/10-compile.t",
         "start" : 1769725367.54832,
         "version" : "1.08"
      },
      {
         "OS" : "linux",
         "abstract" : "Information about the CGI environment",
         "dir" : "/home/runner/work/CGI-Info/CGI-Info",
         "finish" : 1769725368.19472,
         "name" : "CGI-Info",
         "perl" : "5.40.3",
         "run" : "t/20-new.t",
         "start" : 1769725368.16646,
         "version" : "1.08"
      },
      {
         "OS" : "linux",
         "abstract" : "Information about the CGI environment",
         "dir" : "/home/runner/work/CGI-Info/CGI-Info",
         "finish" : 1769725368.88569,
         "name" : "CGI-Info",
         "perl" : "5.40.3",
         "run" : "t/30-basics.t",
         "start" : 1769725368.77226,
         "version" : "1.08"
      },
      {
         "OS" : "linux",
         "abstract" : "Information about the CGI environment",
         "dir" : "/home/runner/work/CGI-Info/CGI-Info",
         "finish" : 1769725369.41049,
         "name" : "CGI-Info",
         "perl" : "5.40.3",
         "run" : "t/40-more.t",
         "start" : 1769725369.4102,
         "version" : "1.08"
      },
      {
         "OS" : "linux",
         "abstract" : "Information about the CGI environment",
         "dir" : "/home/runner/work/CGI-Info/CGI-Info",
         "finish" : 1769725369.85917,
         "name" : "CGI-Info",
         "perl" : "5.40.3",
         "run" : "t/allow.t",
         "start" : 1769725369.77075,
         "version" : "1.08"
      },
      {
         "OS" : "linux",
         "abstract" : "Information about the CGI environment",
         "dir" : "/home/runner/work/CGI-Info/CGI-Info",
         "finish" : 1769725370.31151,
         "name" : "CGI-Info",
         "perl" : "5.40.3",
         "run" : "t/apoc.t",
         "start" : 1769725370.31148,
         "version" : "1.08"
      },
      {
         "OS" : "linux",
         "abstract" : "Information about the CGI environment",
         "dir" : "/home/runner/work/CGI-Info/CGI-Info",
         "finish" : 1769725370.68296,
         "name" : "CGI-Info",
         "perl" : "5.40.3",
         "run" : "t/as_string.t",
         "start" : 1769725370.64694,
         "version" : "1.08"
      },
      {
         "OS" : "linux",
         "abstract" : "Information about the CGI environment",
         "dir" : "/home/runner/work/CGI-Info/CGI-Info",
         "finish" : 1769725371.98578,
         "name" : "CGI-Info",
         "perl" : "5.40.3",
         "run" : "t/bin.t",
         "start" : 1769725371.18868,
         "version" : "1.08"
      },
      {
         "OS" : "linux",
         "abstract" : "Information about the CGI environment",
         "dir" : "/home/runner/work/CGI-Info/CGI-Info",
         "finish" : 1769725371.72497,
         "name" : "CGI-Info",
         "perl" : "5.40.3",
         "run" : "bin/info.pl",
         "start" : 1769725371.69629,
         "version" : "1.08"
      },
      {
         "OS" : "linux",
         "abstract" : "Information about the CGI environment",
         "dir" : "/home/runner/work/CGI-Info/CGI-Info",
         "finish" : 1769725372.28386,
         "name" : "CGI-Info",
         "perl" : "5.40.3",
         "run" : "t/boiler.t",
         "start" : 1769725372.26243,
         "version" : "1.08"
      },
      {
         "OS" : "linux",
         "abstract" : "Information about the CGI environment",
         "dir" : "/home/runner/work/CGI-Info/CGI-Info",
         "finish" : 1769725372.69334,
         "name" : "CGI-Info",
         "perl" : "5.40.3",
         "run" : "t/carp.t",
         "start" : 1769725372.6441,
         "version" : "1.08"
      },
      {
         "OS" : "linux",
         "abstract" : "Information about the CGI environment",
         "dir" : "/home/runner/work/CGI-Info/CGI-Info",
         "finish" : 1769725373.18464,
         "name" : "CGI-Info",
         "perl" : "5.40.3",
         "run" : "t/changes.t",
         "start" : 1769725373.1844,
         "version" : "1.08"
      },
      {
         "OS" : "linux",
         "abstract" : "Information about the CGI environment",
         "dir" : "/home/runner/work/CGI-Info/CGI-Info",
         "finish" : 1769725373.42298,
         "name" : "CGI-Info",
         "perl" : "5.40.3",
         "run" : "t/comment-spelling.t",
         "start" : 1769725373.4227,
         "version" : "1.08"
      },
      {
         "OS" : "linux",
         "abstract" : "Information about the CGI environment",
         "dir" : "/home/runner/work/CGI-Info/CGI-Info",
         "finish" : 1769725373.80203,
         "name" : "CGI-Info",
         "perl" : "5.40.3",
         "run" : "t/config_file.t",
         "start" : 1769725373.69428,
         "version" : "1.08"
      },
      {
         "OS" : "linux",
         "abstract" : "Information about the CGI environment",
         "dir" : "/home/runner/work/CGI-Info/CGI-Info",
         "finish" : 1769725374.44807,
         "name" : "CGI-Info",
         "perl" : "5.40.3",
         "run" : "t/cookies.t",
         "start" : 1769725374.40181,
         "version" : "1.08"
      },
      {
         "OS" : "linux",
         "abstract" : "Information about the CGI environment",
         "dir" : "/home/runner/work/CGI-Info/CGI-Info",
         "finish" : 1769725374.92627,
         "name" : "CGI-Info",
         "perl" : "5.40.3",
         "run" : "t/cover.t",
         "start" : 1769725374.92602,
         "version" : "1.08"
      },
      {
         "OS" : "linux",
         "abstract" : "Information about the CGI environment",
         "dir" : "/home/runner/work/CGI-Info/CGI-Info",
         "finish" : 1769725375.16476,
         "name" : "CGI-Info",
         "perl" : "5.40.3",
         "run" : "t/critic.t",
         "start" : 1769725375.16452,
         "version" : "1.08"
      },
      {
         "OS" : "linux",
         "abstract" : "Information about the CGI environment",
         "dir" : "/home/runner/work/CGI-Info/CGI-Info",
         "finish" : 1769725375.40161,
         "name" : "CGI-Info",
         "perl" : "5.40.3",
         "run" : "t/cv.t",
         "start" : 1769725375.40137,
         "version" : "1.08"
      },
      {
         "OS" : "linux",
         "abstract" : "Information about the CGI environment",
         "dir" : "/home/runner/work/CGI-Info/CGI-Info",
         "finish" : 1769725375.64275,
         "name" : "CGI-Info",
         "perl" : "5.40.3",
         "run" : "t/dependent-modules.t",
         "start" : 1769725375.64249,
         "version" : "1.08"
      },
      {
         "OS" : "linux",
         "abstract" : "Information about the CGI environment",
         "dir" : "/home/runner/work/CGI-Info/CGI-Info",
         "finish" : 1769725375.8831,
         "name" : "CGI-Info",
         "perl" : "5.40.3",
         "run" : "t/dist.t",
         "start" : 1769725375.88282,
         "version" : "1.08"
      },
      {
         "OS" : "linux",
         "abstract" : "Information about the CGI environment",
         "dir" : "/home/runner/work/CGI-Info/CGI-Info",
         "finish" : 1769725376.12444,
         "name" : "CGI-Info",
         "perl" : "5.40.3",
         "run" : "t/eof.t",
         "start" : 1769725376.12413,
         "version" : "1.08"
      },
      {
         "OS" : "linux",
         "abstract" : "Information about the CGI environment",
         "dir" : "/home/runner/work/CGI-Info/CGI-Info",
         "finish" : 1769725376.36435,
         "name" : "CGI-Info",
         "perl" : "5.40.3",
         "run" : "t/eol.t",
         "start" : 1769725376.36409,
         "version" : "1.08"
      },
      {
         "OS" : "linux",
         "abstract" : "Information about the CGI environment",
         "dir" : "/home/runner/work/CGI-Info/CGI-Info",
         "finish" : 1769725376.62182,
         "name" : "CGI-Info",
         "perl" : "5.40.3",
         "run" : "t/expect.t",
         "start" : 1769725376.62116,
         "version" : "1.08"
      },
      {
         "OS" : "linux",
         "abstract" : "Information about the CGI environment",
         "dir" : "/home/runner/work/CGI-Info/CGI-Info",
         "finish" : 1769725376.87016,
         "name" : "CGI-Info",
         "perl" : "5.40.3",
         "run" : "t/fixme.t",
         "start" : 1769725376.86991,
         "version" : "1.08"
      },
      {
         "OS" : "linux",
         "abstract" : "Information about the CGI environment",
         "dir" : "/home/runner/work/CGI-Info/CGI-Info",
         "finish" : 1769725377.05402,
         "name" : "CGI-Info",
         "perl" : "5.40.3",
         "run" : "t/fuzz.t",
         "start" : 1769725377.05399,
         "version" : "1.08"
      },
      {
         "OS" : "linux",
         "abstract" : "Information about the CGI environment",
         "dir" : "/home/runner/work/CGI-Info/CGI-Info",
         "finish" : 1769725377.27306,
         "name" : "CGI-Info",
         "perl" : "5.40.3",
         "run" : "t/gv.t",
         "start" : 1769725377.27283,
         "version" : "1.08"
      },
      {
         "OS" : "linux",
         "abstract" : "Information about the CGI environment",
         "dir" : "/home/runner/work/CGI-Info/CGI-Info",
         "finish" : 1769725377.68603,
         "name" : "CGI-Info",
         "perl" : "5.40.3",
         "run" : "t/is_mobile.t",
         "start" : 1769725377.63069,
         "version" : "1.08"
      },
      {
         "OS" : "linux",
         "abstract" : "Information about the CGI environment",
         "dir" : "/home/runner/work/CGI-Info/CGI-Info",
         "finish" : 1769725378.34514,
         "name" : "CGI-Info",
         "perl" : "5.40.3",
         "run" : "t/is_robot.t",
         "start" : 1769725378.29258,
         "version" : "1.08"
      },
      {
         "OS" : "linux",
         "abstract" : "Information about the CGI environment",
         "dir" : "/home/runner/work/CGI-Info/CGI-Info",
         "finish" : 1769725379.00079,
         "name" : "CGI-Info",
         "perl" : "5.40.3",
         "run" : "t/is_search.t",
         "start" : 1769725378.94807,
         "version" : "1.08"
      },
      {
         "OS" : "linux",
         "abstract" : "Information about the CGI environment",
         "dir" : "/home/runner/work/CGI-Info/CGI-Info",
         "finish" : 1769725379.64182,
         "name" : "CGI-Info",
         "perl" : "5.40.3",
         "run" : "t/is_tablet.t",
         "start" : 1769725379.60153,
         "version" : "1.08"
      },
      {
         "OS" : "linux",
         "abstract" : "Information about the CGI environment",
         "dir" : "/home/runner/work/CGI-Info/CGI-Info",
         "finish" : 1769725380.25232,
         "name" : "CGI-Info",
         "perl" : "5.40.3",
         "run" : "t/json.t",
         "start" : 1769725380.22963,
         "version" : "1.08"
      },
      {
         "OS" : "linux",
         "abstract" : "Information about the CGI environment",
         "dir" : "/home/runner/work/CGI-Info/CGI-Info",
         "finish" : 1769725380.71609,
         "name" : "CGI-Info",
         "perl" : "5.40.3",
         "run" : "t/kwalitee.t",
         "start" : 1769725380.7158,
         "version" : "1.08"
      },
      {
         "OS" : "linux",
         "abstract" : "Information about the CGI environment",
         "dir" : "/home/runner/work/CGI-Info/CGI-Info",
         "finish" : 1769725381.09193,
         "name" : "CGI-Info",
         "perl" : "5.40.3",
         "run" : "t/logdir.t",
         "start" : 1769725381.06575,
         "version" : "1.08"
      },
      {
         "OS" : "linux",
         "abstract" : "Information about the CGI environment",
         "dir" : "/home/runner/work/CGI-Info/CGI-Info",
         "finish" : 1769725381.70695,
         "name" : "CGI-Info",
         "perl" : "5.40.3",
         "run" : "t/logger.t",
         "start" : 1769725381.67544,
         "version" : "1.08"
      },
      {
         "OS" : "linux",
         "abstract" : "Information about the CGI environment",
         "dir" : "/home/runner/work/CGI-Info/CGI-Info",
         "finish" : 1769725382.18189,
         "name" : "CGI-Info",
         "perl" : "5.40.3",
         "run" : "t/manifest.t",
         "start" : 1769725382.18161,
         "version" : "1.08"
      },
      {
         "OS" : "linux",
         "abstract" : "Information about the CGI environment",
         "dir" : "/home/runner/work/CGI-Info/CGI-Info",
         "finish" : 1769725382.42178,
         "name" : "CGI-Info",
         "perl" : "5.40.3",
         "run" : "t/metrics.t",
         "start" : 1769725382.42151,
         "version" : "1.08"
      },
      {
         "OS" : "linux",
         "abstract" : "Information about the CGI environment",
         "dir" : "/home/runner/work/CGI-Info/CGI-Info",
         "finish" : 1769725382.65606,
         "name" : "CGI-Info",
         "perl" : "5.40.3",
         "run" : "t/minimum.t",
         "start" : 1769725382.65581,
         "version" : "1.08"
      },
      {
         "OS" : "linux",
         "abstract" : "Information about the CGI environment",
         "dir" : "/home/runner/work/CGI-Info/CGI-Info",
         "finish" : 1769725382.8915,
         "name" : "CGI-Info",
         "perl" : "5.40.3",
         "run" : "t/modules-used.t",
         "start" : 1769725382.89124,
         "version" : "1.08"
      },
      {
         "OS" : "linux",
         "abstract" : "Information about the CGI environment",
         "dir" : "/home/runner/work/CGI-Info/CGI-Info",
         "finish" : 1769725383.1267,
         "name" : "CGI-Info",
         "perl" : "5.40.3",
         "run" : "t/namespaces.t",
         "start" : 1769725383.12644,
         "version" : "1.08"
      },
      {
         "OS" : "linux",
         "abstract" : "Information about the CGI environment",
         "dir" : "/home/runner/work/CGI-Info/CGI-Info",
         "finish" : 1769725383.36299,
         "name" : "CGI-Info",
         "perl" : "5.40.3",
         "run" : "t/no404s.t",
         "start" : 1769725383.36274,
         "version" : "1.08"
      },
      {
         "OS" : "linux",
         "abstract" : "Information about the CGI environment",
         "dir" : "/home/runner/work/CGI-Info/CGI-Info",
         "finish" : 1769725383.60017,
         "name" : "CGI-Info",
         "perl" : "5.40.3",
         "run" : "t/noopentickets.t",
         "start" : 1769725383.59991,
         "version" : "1.08"
      },
      {
         "OS" : "linux",
         "abstract" : "Information about the CGI environment",
         "dir" : "/home/runner/work/CGI-Info/CGI-Info",
         "finish" : 1769725383.83663,
         "name" : "CGI-Info",
         "perl" : "5.40.3",
         "run" : "t/noplan.t",
         "start" : 1769725383.83637,
         "version" : "1.08"
      },
      {
         "OS" : "linux",
         "abstract" : "Information about the CGI environment",
         "dir" : "/home/runner/work/CGI-Info/CGI-Info",
         "finish" : 1769725384.19131,
         "name" : "CGI-Info",
         "perl" : "5.40.3",
         "run" : "t/object_configure.t",
         "start" : 1769725384.11416,
         "version" : "1.08"
      },
      {
         "OS" : "linux",
         "abstract" : "Information about the CGI environment",
         "dir" : "/home/runner/work/CGI-Info/CGI-Info",
         "finish" : 1769725384.83651,
         "name" : "CGI-Info",
         "perl" : "5.40.3",
         "run" : "t/param.t",
         "start" : 1769725384.77206,
         "version" : "1.08"
      },
      {
         "OS" : "linux",
         "abstract" : "Information about the CGI environment",
         "dir" : "/home/runner/work/CGI-Info/CGI-Info",
         "finish" : 1769725385.62739,
         "name" : "CGI-Info",
         "perl" : "5.40.3",
         "run" : "t/params.t",
         "start" : 1769725385.43784,
         "version" : "1.08"
      },
      {
         "OS" : "linux",
         "abstract" : "Information about the CGI environment",
         "dir" : "/home/runner/work/CGI-Info/CGI-Info",
         "finish" : 1769725386.17264,
         "name" : "CGI-Info",
         "perl" : "5.40.3",
         "run" : "t/pod-cm.t",
         "start" : 1769725386.17236,
         "version" : "1.08"
      },
      {
         "OS" : "linux",
         "abstract" : "Information about the CGI environment",
         "dir" : "/home/runner/work/CGI-Info/CGI-Info",
         "finish" : 1769725386.40812,
         "name" : "CGI-Info",
         "perl" : "5.40.3",
         "run" : "t/pod-coverage.t",
         "start" : 1769725386.4079,
         "version" : "1.08"
      },
      {
         "OS" : "linux",
         "abstract" : "Information about the CGI environment",
         "dir" : "/home/runner/work/CGI-Info/CGI-Info",
         "finish" : 1769725386.64009,
         "name" : "CGI-Info",
         "perl" : "5.40.3",
         "run" : "t/pod-links.t",
         "start" : 1769725386.63988,
         "version" : "1.08"
      },
      {
         "OS" : "linux",
         "abstract" : "Information about the CGI environment",
         "dir" : "/home/runner/work/CGI-Info/CGI-Info",
         "finish" : 1769725386.87349,
         "name" : "CGI-Info",
         "perl" : "5.40.3",
         "run" : "t/pod-snippets.t",
         "start" : 1769725386.87323,
         "version" : "1.08"
      },
      {
         "OS" : "linux",
         "abstract" : "Information about the CGI environment",
         "dir" : "/home/runner/work/CGI-Info/CGI-Info",
         "finish" : 1769725387.10926,
         "name" : "CGI-Info",
         "perl" : "5.40.3",
         "run" : "t/pod-spelling.t",
         "start" : 1769725387.10896,
         "version" : "1.08"
      },
      {
         "OS" : "linux",
         "abstract" : "Information about the CGI environment",
         "dir" : "/home/runner/work/CGI-Info/CGI-Info",
         "finish" : 1769725387.34622,
         "name" : "CGI-Info",
         "perl" : "5.40.3",
         "run" : "t/pod-synopsis.t",
         "start" : 1769725387.34598,
         "version" : "1.08"
      },
      {
         "OS" : "linux",
         "abstract" : "Information about the CGI environment",
         "dir" : "/home/runner/work/CGI-Info/CGI-Info",
         "finish" : 1769725387.58038,
         "name" : "CGI-Info",
         "perl" : "5.40.3",
         "run" : "t/pod.t",
         "start" : 1769725387.58013,
         "version" : "1.08"
      },
      {
         "OS" : "linux",
         "abstract" : "Information about the CGI environment",
         "dir" : "/home/runner/work/CGI-Info/CGI-Info",
         "finish" : 1769725387.84114,
         "name" : "CGI-Info",
         "perl" : "5.40.3",
         "run" : "t/port.t",
         "start" : 1769725387.84086,
         "version" : "1.08"
      },
      {
         "OS" : "linux",
         "abstract" : "Information about the CGI environment",
         "dir" : "/home/runner/work/CGI-Info/CGI-Info",
         "finish" : 1769725388.08518,
         "name" : "CGI-Info",
         "perl" : "5.40.3",
         "run" : "t/prereq.t",
         "start" : 1769725388.08488,
         "version" : "1.08"
      },
      {
         "OS" : "linux",
         "abstract" : "Information about the CGI environment",
         "dir" : "/home/runner/work/CGI-Info/CGI-Info",
         "finish" : 1769725388.47851,
         "name" : "CGI-Info",
         "perl" : "5.40.3",
         "run" : "t/protocol.t",
         "start" : 1769725388.44289,
         "version" : "1.08"
      },
      {
         "OS" : "linux",
         "abstract" : "Information about the CGI environment",
         "dir" : "/home/runner/work/CGI-Info/CGI-Info",
         "finish" : 1769725389.09304,
         "name" : "CGI-Info",
         "perl" : "5.40.3",
         "run" : "t/rootdir.t",
         "start" : 1769725389.06268,
         "version" : "1.08"
      },
      {
         "OS" : "linux",
         "abstract" : "Information about the CGI environment",
         "dir" : "/home/runner/work/CGI-Info/CGI-Info",
         "finish" : 1769725389.73889,
         "name" : "CGI-Info",
         "perl" : "5.40.3",
         "run" : "t/script.t",
         "start" : 1769725389.68714,
         "version" : "1.08"
      },
      {
         "OS" : "linux",
         "abstract" : "Information about the CGI environment",
         "dir" : "/home/runner/work/CGI-Info/CGI-Info",
         "finish" : 1769725390.38878,
         "name" : "CGI-Info",
         "perl" : "5.40.3",
         "run" : "t/site.t",
         "start" : 1769725390.35629,
         "version" : "1.08"
      },
      {
         "OS" : "linux",
         "abstract" : "Information about the CGI environment",
         "dir" : "/home/runner/work/CGI-Info/CGI-Info",
         "finish" : 1769725391.01895,
         "name" : "CGI-Info",
         "perl" : "5.40.3",
         "run" : "t/status.t",
         "start" : 1769725390.97872,
         "version" : "1.08"
      },
      {
         "OS" : "linux",
         "abstract" : "Information about the CGI environment",
         "dir" : "/home/runner/work/CGI-Info/CGI-Info",
         "finish" : 1769725391.49155,
         "name" : "CGI-Info",
         "perl" : "5.40.3",
         "run" : "t/strict.t",
         "start" : 1769725391.49129,
         "version" : "1.08"
      },
      {
         "OS" : "linux",
         "abstract" : "Information about the CGI environment",
         "dir" : "/home/runner/work/CGI-Info/CGI-Info",
         "finish" : 1769725391.72866,
         "name" : "CGI-Info",
         "perl" : "5.40.3",
         "run" : "t/tabs.t",
         "start" : 1769725391.72839,
         "version" : "1.08"
      },
      {
         "OS" : "linux",
         "abstract" : "Information about the CGI environment",
         "dir" : "/home/runner/work/CGI-Info/CGI-Info",
         "finish" : 1769725391.96477,
         "name" : "CGI-Info",
         "perl" : "5.40.3",
         "run" : "t/taint.t",
         "start" : 1769725391.96452,
         "version" : "1.08"
      },
      {
         "OS" : "linux",
         "abstract" : "Information about the CGI environment",
         "dir" : "/home/runner/work/CGI-Info/CGI-Info",
         "finish" : 1769725392.35582,
         "name" : "CGI-Info",
         "perl" : "5.40.3",
         "run" : "t/tmpdir.t",
         "start" : 1769725392.31514,
         "version" : "1.08"
      },
      {
         "OS" : "linux",
         "abstract" : "Information about the CGI environment",
         "dir" : "/home/runner/work/CGI-Info/CGI-Info",
         "finish" : 1769725392.85629,
         "name" : "CGI-Info",
         "perl" : "5.40.3",
         "run" : "t/untaint.t",
         "start" : 1769725392.85584,
         "version" : "1.08"
      },
      {
         "OS" : "linux",
         "abstract" : "Information about the CGI environment",
         "dir" : "/home/runner/work/CGI-Info/CGI-Info",
         "finish" : 1769725393.0982,
         "name" : "CGI-Info",
         "perl" : "5.40.3",
         "run" : "t/unused.t",
         "start" : 1769725393.09798,
         "version" : "1.08"
      },
      {
         "OS" : "linux",
         "abstract" : "Information about the CGI environment",
         "dir" : "/home/runner/work/CGI-Info/CGI-Info",
         "finish" : 1769725393.33331,
         "name" : "CGI-Info",
         "perl" : "5.40.3",
         "run" : "t/vars.t",
         "start" : 1769725393.33307,
         "version" : "1.08"
      },
      {
         "OS" : "linux",
         "abstract" : "Information about the CGI environment",
         "dir" : "/home/runner/work/CGI-Info/CGI-Info",
         "finish" : 1769725393.56875,
         "name" : "CGI-Info",
         "perl" : "5.40.3",
         "run" : "t/version.t",
         "start" : 1769725393.56849,
         "version" : "1.08"
      },
      {
         "OS" : "linux",
         "abstract" : "Information about the CGI environment",
         "dir" : "/home/runner/work/CGI-Info/CGI-Info",
         "finish" : 1769725393.97731,
         "name" : "CGI-Info",
         "perl" : "5.40.3",
         "run" : "t/waf.t",
         "start" : 1769725393.91951,
         "version" : "1.08"
      },
      {
         "OS" : "linux",
         "abstract" : "Information about the CGI environment",
         "dir" : "/home/runner/work/CGI-Info/CGI-Info",
         "finish" : 1769725394.62617,
         "name" : "CGI-Info",
         "perl" : "5.40.3",
         "run" : "t/xml.t",
         "start" : 1769725394.60131,
         "version" : "1.08"
      }
   ],
   "summary" : {
      "Total" : {
         "branch" : {
            "covered" : 369,
            "error" : 129,
            "percentage" : 74.0963855421687,
            "total" : 498,
            "uncoverable" : 0
         },
         "condition" : {
            "covered" : 178,
            "error" : 125,
            "percentage" : 58.7458745874587,
            "total" : 303,
            "uncoverable" : 0
         },
         "statement" : {
            "covered" : 692,
            "error" : 109,
            "percentage" : 86.3920099875156,
            "total" : 801
         },
         "subroutine" : {
            "covered" : 64,
            "error" : 1,
            "percentage" : 98.4615384615385,
            "total" : 65
         },
         "total" : {
            "covered" : 1303,
            "error" : 364,
            "percentage" : 78.1643671265747,
            "total" : 1667,
            "uncoverable" : 0
         }
      },
      "bin/info.pl" : {
         "branch" : {
            "covered" : 2,
            "error" : 6,
            "percentage" : 25,
            "total" : 8,
            "uncoverable" : 0
         },
         "statement" : {
            "covered" : 27,
            "error" : 9,
            "percentage" : 75,
            "total" : 36
         },
         "subroutine" : {
            "covered" : 3,
            "percentage" : 100,
            "total" : 3
         },
         "total" : {
            "covered" : 32,
            "error" : 15,
            "percentage" : 68.0851063829787,
            "total" : 47,
            "uncoverable" : 0
         }
      },
      "blib/lib/CGI/Info.pm" : {
         "branch" : {
            "covered" : 367,
            "error" : 123,
            "percentage" : 74.8979591836735,
            "total" : 490,
            "uncoverable" : 0
         },
         "condition" : {
            "covered" : 178,
            "error" : 125,
            "percentage" : 58.7458745874587,
            "total" : 303,
            "uncoverable" : 0
         },
         "statement" : {
            "covered" : 665,
            "error" : 100,
            "percentage" : 86.9281045751634,
            "total" : 765
         },
         "subroutine" : {
            "covered" : 61,
            "error" : 1,
            "percentage" : 98.3870967741936,
            "total" : 62
         },
         "total" : {
            "covered" : 1271,
            "error" : 349,
            "percentage" : 78.4567901234568,
            "total" : 1620,
            "uncoverable" : 0
         }
      }
   }
}
